{
  "$schema": "https://json.schemastore.org/launchsettings.json",
  "profiles": {
    "Development": {
      "commandName": "Project",
      "dotnetRunMessages": true,
      "launchBrowser": true,
      "applicationUrl": "https://localhost:7890;http://localhost:5000",
      "environmentVariables": {
        "ASPNETCORE_ENVIRONMENT": "Development",
        "ASPNETCORE_HTTPS_PORT": "7890",
        "DOTNET_WATCH_SUPPRESS_STATIC_ASSETS_LOADER": "true",
        "DOTNET_WATCH_SUPPRESS_STATIC_FILE_HANDLING": "true"
      }
    },
    "Production": {
      "commandName": "Project",
      "dotnetRunMessages": true,
      "launchBrowser": true,
      "applicationUrl": "https://localhost:7890;http://localhost:5000",
      "environmentVariables": {
        "ASPNETCORE_ENVIRONMENT": "Production",
        "ASPNETCORE_HTTPS_PORT": "7890"
      }
    },
    "Http": {
      "commandName": "Project",
      "dotnetRunMessages": true,
      "launchBrowser": true,
      "applicationUrl": "http://localhost:5000",
      "environmentVariables": {
        "ASPNETCORE_ENVIRONMENT": "Development",
        "DOTNET_WATCH_SUPPRESS_STATIC_ASSETS_LOADER": "true",
        "DOTNET_WATCH_SUPPRESS_STATIC_FILE_HANDLING": "true"
      }
    },
    "CloudflareTunnel": {
      "commandName": "Project",
      "dotnetRunMessages": true,
      "launchBrowser": false,
      "applicationUrl": "http://localhost:5000",
      "environmentVariables": {
        "ASPNETCORE_ENVIRONMENT": "Production",
        "ASPNETCORE_FORWARDEDHEADERS_ENABLED": "true"
      }
    }
  }
}
